fasr/__init__.py
fasr/__main__.py
fasr/config.py
fasr/normalizer.py
fasr/asset/__init__.py
fasr/asset/example/asr_example.wav
fasr/asset/example/hotwords.txt
fasr/asset/example/vad_example.wav
fasr/asset/fsmn-vad/am.mvn
fasr/asset/fsmn-vad/config.yaml
fasr/asset/fsmn-vad/configuration.json
fasr/asset/fsmn-vad/model.onnx
fasr/asset/fsmn-vad/model.pt
fasr/asset/wetext/.mdl
fasr/asset/wetext/.msc
fasr/asset/wetext/.mv
fasr/asset/wetext/README.md
fasr/asset/wetext/configuration.json
fasr/asset/wetext/en/tn/tagger.fst
fasr/asset/wetext/en/tn/verbalizer.fst
fasr/asset/wetext/zh/itn/tagger.fst
fasr/asset/wetext/zh/itn/tagger_enable_0_to_9.fst
fasr/asset/wetext/zh/itn/verbalizer.fst
fasr/asset/wetext/zh/tn/tagger.fst
fasr/asset/wetext/zh/tn/verbalizer.fst
fasr/asset/wetext/zh/tn/verbalizer_remove_erhua.fst
fasr/components/__init__.py
fasr/components/base.py
fasr/components/detector.py
fasr/components/loader.py
fasr/components/recogmizer.py
fasr/components/sentencizer.py
fasr/components/stream/__init__.py
fasr/components/stream/base.py
fasr/components/stream/stream_detector.py
fasr/components/stream/stream_recognizer.py
fasr/data/__init__.py
fasr/data/audio.py
fasr/data/eval.py
fasr/data/stream.py
fasr/data/waveform.py
fasr/layers/__init__.py
fasr/layers/embeddings.py
fasr/layers/fsmn.py
fasr/models/__init__.py
fasr/models/base.py
fasr/models/asr/__init__.py
fasr/models/asr/base.py
fasr/models/asr/dolphin.py
fasr/models/asr/paraformer.py
fasr/models/asr/seaco_paraformer.py
fasr/models/asr/sensevoice.py
fasr/models/asr/firered/__init__.py
fasr/models/asr/firered/conformer_encoder.py
fasr/models/asr/firered/feats.py
fasr/models/asr/firered/firered_aed.py
fasr/models/asr/firered/tokenizer.py
fasr/models/asr/firered/transformer_decoder.py
fasr/models/punc/__init__.py
fasr/models/punc/base.py
fasr/models/punc/ct_transformer.py
fasr/models/stream_asr/__init__.py
fasr/models/stream_asr/base.py
fasr/models/stream_asr/stream_paraformer.py
fasr/models/stream_asr/stream_sensevoice.py
fasr-0.3.6.dist-info/METADATA
fasr-0.3.6.dist-info/WHEEL
fasr-0.3.6.dist-info/entry_points.txt
fasr-0.3.6.dist-info/RECORD
