Metadata-Version: 2.4
Name: fasr
Version: 0.3.6
Summary: FASR: Fast Automatic Speech Recognition
Author-email: wangmengdi06 <wangmengdi06@58.com>
Requires-Python: <3.13,>=3.10
Requires-Dist: aiofiles>=24.1.0
Requires-Dist: aiohttp>=3.10.10
Requires-Dist: asr-decoder>=0.1.1
Requires-Dist: catalogue>=2.0.10
Requires-Dist: confection>=0.1.5
Requires-Dist: docarray==0.40
Requires-Dist: editdistance>=0.8.1
Requires-Dist: funasr-onnx>=0.4.1
Requires-Dist: funasr>=1.2.6
Requires-Dist: huggingface-hub>=0.27.0
Requires-Dist: hydra-core>=1.3.2
Requires-Dist: joblib>=1.4.2
Requires-Dist: jsonargparse[signatures,urls]>=4.38
Requires-Dist: kaldifst>=1.7.14
Requires-Dist: librosa>=0.9.2
Requires-Dist: lightning-utilities>=0.11.8
Requires-Dist: loguru>=0.7.2
Requires-Dist: modelscope>=1.19.1
Requires-Dist: numpy==1.23.4
Requires-Dist: online-fbank>=0.0.4
Requires-Dist: onnxruntime
Requires-Dist: protobuf>=3.20.0
Requires-Dist: pydantic>=2.9.2
Requires-Dist: pydub>=0.25.1
Requires-Dist: sentencepiece>=0.1.97
Requires-Dist: torch-complex>=0.4.4
Requires-Dist: torch>=2.1.0
Requires-Dist: torchaudio>=2.1.0
Requires-Dist: wasabi>=1.1.3
Provides-Extra: benchmark
Requires-Dist: pyaudio>=0.2.14; extra == 'benchmark'
Provides-Extra: dolphin
Requires-Dist: dataoceanai-dolphin>=20250519; extra == 'dolphin'
Provides-Extra: litdata
Requires-Dist: litdata>=0.2.47; extra == 'litdata'
Provides-Extra: serve
Requires-Dist: fastapi>=0.115.12; extra == 'serve'
Requires-Dist: websockets>=15.0.1; extra == 'serve'
Requires-Dist: wsproto>=1.2.0; extra == 'serve'
